db/__init__.py
db/conn.py
setup_2-0.1.0.dist-info/METADATA
setup_2-0.1.0.dist-info/WHEEL
setup_2-0.1.0.dist-info/top_level.txt
setup_2-0.1.0.dist-info/RECORD
